{
  "snap": {
    "AAATEC": {
      "price": 95.39,
      "prevClose": 94.02,
      "exchange": "NSE",
      "lastTradeTime": 1779887560,
      "marketState": "CLOSED",
      "savedAt": 1779887560068
    },
    "ADDPRO": {
      "price": 7.31,
      "prevClose": 7.14,
      "exchange": "BSE",
      "lastTradeTime": 1779887561,
      "marketState": "CLOSED",
      "savedAt": 1779887561066
    },
    "AFL": {
      "price": 127.15,
      "prevClose": 125.24,
      "exchange": "NSE",
      "lastTradeTime": 1779887561,
      "marketState": "CLOSED",
      "savedAt": 1779887561247
    },
    "AGSTRA": {
      "price": 2.24,
      "prevClose": 2.24,
      "exchange": "NSE",
      "lastTradeTime": 1779887561,
      "marketState": "CLOSED",
      "savedAt": 1779887561580
    },
    "AJASOY": {
      "price": 24.1,
      "prevClose": 23.93,
      "exchange": "BSE",
      "lastTradeTime": 1779887562,
      "marketState": "CLOSED",
      "savedAt": 1779887562340
    },
    "AMBCE": {
      "price": 459.75,
      "prevClose": 450.4,
      "exchange": "NSE",
      "lastTradeTime": 1779887562,
      "marketState": "CLOSED",
      "savedAt": 1779887562598
    },
    "ANUPHA": {
      "price": 76.67,
      "prevClose": 76.47,
      "exchange": "NSE",
      "lastTradeTime": 1779887562,
      "marketState": "CLOSED",
      "savedAt": 1779887562762
    },
    "ASIEAS": {
      "price": 161.67,
      "prevClose": 165.31,
      "exchange": "NSE",
      "lastTradeTime": 1779887562,
      "marketState": "CLOSED",
      "savedAt": 1779887562971
    },
    "ASSSTO": {
      "price": 24.66,
      "prevClose": 23.91,
      "exchange": "BSE",
      "lastTradeTime": 1779887563,
      "marketState": "CLOSED",
      "savedAt": 1779887563651
    },
    "AVAFEE": {
      "price": 1297.4,
      "prevClose": 1334.9,
      "exchange": "NSE",
      "lastTradeTime": 1779887563,
      "marketState": "CLOSED",
      "savedAt": 1779887563955
    },
    "AXIBAN": {
      "price": 1304.1,
      "prevClose": 1301.5,
      "exchange": "NSE",
      "lastTradeTime": 1779887565,
      "marketState": "CLOSED",
      "savedAt": 1779887565186
    },
    "BANBAR": {
      "price": 270.95,
      "prevClose": 270.55,
      "exchange": "NSE",
      "lastTradeTime": 1779887565,
      "marketState": "CLOSED",
      "savedAt": 1779887565413
    },
    "BANFIN": {
      "price": 7.11,
      "prevClose": 6.98,
      "exchange": "BSE",
      "lastTradeTime": 1779887566,
      "marketState": "CLOSED",
      "savedAt": 1779887566226
    },
    "BERSEC": {
      "price": 27.88,
      "prevClose": 28.44,
      "exchange": "BSE",
      "lastTradeTime": 1779887566,
      "marketState": "CLOSED",
      "savedAt": 1779887566993
    },
    "BHAELE": {
      "price": 419.1,
      "prevClose": 420.65,
      "exchange": "NSE",
      "lastTradeTime": 1779887567,
      "marketState": "CLOSED",
      "savedAt": 1779887567232
    },
    "BHEL": {
      "price": 422.35,
      "prevClose": 417.75,
      "exchange": "NSE",
      "lastTradeTime": 1779887567,
      "marketState": "CLOSED",
      "savedAt": 1779887567444
    },
    "BODCHE": {
      "price": 73.35,
      "prevClose": 74.74,
      "exchange": "NSE",
      "lastTradeTime": 1779887567,
      "marketState": "CLOSED",
      "savedAt": 1779887567646
    },
    "CALSOF": {
      "price": 19.12,
      "prevClose": 19.84,
      "exchange": "NSE",
      "lastTradeTime": 1779887567,
      "marketState": "CLOSED",
      "savedAt": 1779887567922
    },
    "CNKFIN": {
      "price": 0.35,
      "prevClose": 0.35,
      "exchange": "NSE",
      "lastTradeTime": 1779887568,
      "marketState": "CLOSED",
      "savedAt": 1779887568076
    },
    "CPSETF": {
      "price": 103.99,
      "prevClose": 103.62,
      "exchange": "NSE",
      "lastTradeTime": 1779887570,
      "marketState": "CLOSED",
      "savedAt": 1779887570724
    },
    "DAVSUG": {
      "price": 4.13,
      "prevClose": 4.07,
      "exchange": "NSE",
      "lastTradeTime": 1779887570,
      "marketState": "CLOSED",
      "savedAt": 1779887570888
    },
    "DELLIM": {
      "price": 459.75,
      "prevClose": 465.25,
      "exchange": "NSE",
      "lastTradeTime": 1779887571,
      "marketState": "CLOSED",
      "savedAt": 1779887571052
    },
    "DEVIN": {
      "price": 117.16,
      "prevClose": 116.5,
      "exchange": "NSE",
      "lastTradeTime": 1779887571,
      "marketState": "CLOSED",
      "savedAt": 1779887571315
    },
    "DIVLAB": {
      "price": 6797.5,
      "prevClose": 6743.0,
      "exchange": "NSE",
      "lastTradeTime": 1779887571,
      "marketState": "CLOSED",
      "savedAt": 1779887571546
    },
    "DOLINV": {
      "price": 75.39,
      "prevClose": 74.75,
      "exchange": "NSE",
      "lastTradeTime": 1779887571,
      "marketState": "CLOSED",
      "savedAt": 1779887571733
    },
    "DPSLIM": {
      "price": 8.47,
      "prevClose": 8.51,
      "exchange": "NSE",
      "lastTradeTime": 1779887571,
      "marketState": "CLOSED",
      "savedAt": 1779887571928
    },
    "EASTRI": {
      "price": 7.41,
      "prevClose": 8.02,
      "exchange": "NSE",
      "lastTradeTime": 1779887572,
      "marketState": "CLOSED",
      "savedAt": 1779887572089
    },
    "EIHLIM": {
      "price": 313.2,
      "prevClose": 319.9,
      "exchange": "NSE",
      "lastTradeTime": 1779887572,
      "marketState": "CLOSED",
      "savedAt": 1779887572309
    },
    "ELECAS": {
      "price": 81.65,
      "prevClose": 82.13,
      "exchange": "NSE",
      "lastTradeTime": 1779887572,
      "marketState": "CLOSED",
      "savedAt": 1779887572530
    },
    "EXIIND": {
      "price": 394.15,
      "prevClose": 368.0,
      "exchange": "NSE",
      "lastTradeTime": 1779887573,
      "marketState": "CLOSED",
      "savedAt": 1779887573749
    },
    "FCSSOF": {
      "price": 1.5,
      "prevClose": 1.52,
      "exchange": "NSE",
      "lastTradeTime": 1779887573,
      "marketState": "CLOSED",
      "savedAt": 1779887573926
    },
    "FILFAS": {
      "price": 0.23,
      "prevClose": 0.24,
      "exchange": "NSE",
      "lastTradeTime": 1779887574,
      "marketState": "CLOSED",
      "savedAt": 1779887574103
    },
    "FIRSOU": {
      "price": 264.97,
      "prevClose": 275.5,
      "exchange": "NSE",
      "lastTradeTime": 1779887574,
      "marketState": "CLOSED",
      "savedAt": 1779887574289
    },
    "FUTRE": {
      "price": 2.28,
      "prevClose": 2.28,
      "exchange": "NSE",
      "lastTradeTime": 1779887574,
      "marketState": "CLOSED",
      "savedAt": 1779887574559
    },
    "GENLAB": {
      "price": 11.77,
      "prevClose": 12.11,
      "exchange": "BSE",
      "lastTradeTime": 1779887575,
      "marketState": "CLOSED",
      "savedAt": 1779887575356
    },
    "GMRINF": {
      "price": 97.84,
      "prevClose": 96.6,
      "exchange": "NSE",
      "lastTradeTime": 1779887575,
      "marketState": "CLOSED",
      "savedAt": 1779887575517
    },
    "GMRPOW": {
      "price": 109.57,
      "prevClose": 106.6,
      "exchange": "NSE",
      "lastTradeTime": 1779887575,
      "marketState": "CLOSED",
      "savedAt": 1779887575671
    },
    "HCLINF": {
      "price": 12.74,
      "prevClose": 11.58,
      "exchange": "NSE",
      "lastTradeTime": 1779887575,
      "marketState": "CLOSED",
      "savedAt": 1779887575884
    },
    "HDFBAN": {
      "price": 758.65,
      "prevClose": 780.25,
      "exchange": "NSE",
      "lastTradeTime": 1779887576,
      "marketState": "CLOSED",
      "savedAt": 1779887576193
    },
    "HINCON": {
      "price": 23.21,
      "prevClose": 21.95,
      "exchange": "NSE",
      "lastTradeTime": 1779887577,
      "marketState": "CLOSED",
      "savedAt": 1779887577431
    },
    "HINZIN": {
      "price": 648.85,
      "prevClose": 647.65,
      "exchange": "NSE",
      "lastTradeTime": 1779887577,
      "marketState": "CLOSED",
      "savedAt": 1779887577655
    },
    "ICIBAN": {
      "price": 1272.7,
      "prevClose": 1280.9,
      "exchange": "NSE",
      "lastTradeTime": 1779887577,
      "marketState": "CLOSED",
      "savedAt": 1779887577873
    },
    "ICIGOL": {
      "price": 133.54,
      "prevClose": 134.25,
      "exchange": "NSE",
      "lastTradeTime": 1779887578,
      "marketState": "CLOSED",
      "savedAt": 1779887578083
    },
    "IGAMOT": {
      "price": 382.8,
      "prevClose": 385.6,
      "exchange": "NSE",
      "lastTradeTime": 1779887578,
      "marketState": "CLOSED",
      "savedAt": 1779887578367
    },
    "INDCEM": {
      "price": 400.6,
      "prevClose": 403.3,
      "exchange": "NSE",
      "lastTradeTime": 1779887578,
      "marketState": "CLOSED",
      "savedAt": 1779887578637
    },
    "INDR": {
      "price": 99.19,
      "prevClose": 99.25,
      "exchange": "NSE",
      "lastTradeTime": 1779887578,
      "marketState": "CLOSED",
      "savedAt": 1779887578816
    },
    "INFINC": {
      "price": 14.05,
      "prevClose": 13.98,
      "exchange": "NSE",
      "lastTradeTime": 1779887578,
      "marketState": "CLOSED",
      "savedAt": 1779887578985
    },
    "JAIASS": {
      "price": 2.42,
      "prevClose": 2.42,
      "exchange": "NSE",
      "lastTradeTime": 1779887579,
      "marketState": "CLOSED",
      "savedAt": 1779887579279
    },
    "JAIIRR": {
      "price": 30.35,
      "prevClose": 30.25,
      "exchange": "NSE",
      "lastTradeTime": 1779887579,
      "marketState": "CLOSED",
      "savedAt": 1779887579475
    },
    "JAYNE": {
      "price": 104.51,
      "prevClose": 103.4,
      "exchange": "NSE",
      "lastTradeTime": 1779887580,
      "marketState": "CLOSED",
      "savedAt": 1779887580684
    },
    "JIOFIN": {
      "price": 242.89,
      "prevClose": 241.0,
      "exchange": "NSE",
      "lastTradeTime": 1779887580,
      "marketState": "CLOSED",
      "savedAt": 1779887580852
    },
    "JKTYRE": {
      "price": 413.3,
      "prevClose": 394.15,
      "exchange": "NSE",
      "lastTradeTime": 1779887581,
      "marketState": "CLOSED",
      "savedAt": 1779887581133
    },
    "JUNHOT": {
      "price": 196.83,
      "prevClose": 198.0,
      "exchange": "NSE",
      "lastTradeTime": 1779887581,
      "marketState": "CLOSED",
      "savedAt": 1779887581294
    },
    "KANNER": {
      "price": 218.34,
      "prevClose": 218.0,
      "exchange": "NSE",
      "lastTradeTime": 1779887581,
      "marketState": "CLOSED",
      "savedAt": 1779887581503
    },
    "KARBAN": {
      "price": 271.85,
      "prevClose": 267.8,
      "exchange": "NSE",
      "lastTradeTime": 1779887581,
      "marketState": "CLOSED",
      "savedAt": 1779887581764
    },
    "KCPSUG": {
      "price": 24.62,
      "prevClose": 24.57,
      "exchange": "NSE",
      "lastTradeTime": 1779887581,
      "marketState": "CLOSED",
      "savedAt": 1779887581998
    },
    "KITGAR": {
      "price": 161.19,
      "prevClose": 163.25,
      "exchange": "NSE",
      "lastTradeTime": 1779887582,
      "marketState": "CLOSED",
      "savedAt": 1779887582248
    },
    "KMSUG": {
      "price": 27.36,
      "prevClose": 27.37,
      "exchange": "NSE",
      "lastTradeTime": 1779887582,
      "marketState": "CLOSED",
      "savedAt": 1779887582417
    },
    "KOTPET": {
      "price": 126.12,
      "prevClose": 127.67,
      "exchange": "NSE",
      "lastTradeTime": 1779887582,
      "marketState": "CLOSED",
      "savedAt": 1779887582623
    },
    "KPITEC": {
      "price": 328.1,
      "prevClose": 324.6,
      "exchange": "NSE",
      "lastTradeTime": 1779887583,
      "marketState": "CLOSED",
      "savedAt": 1779887583875
    },
    "LANHOL": {
      "price": 24.39,
      "prevClose": 24.5,
      "exchange": "NSE",
      "lastTradeTime": 1779887584,
      "marketState": "CLOSED",
      "savedAt": 1779887584037
    },
    "LARTOU": {
      "price": 4047.5,
      "prevClose": 4037.0,
      "exchange": "NSE",
      "lastTradeTime": 1779887584,
      "marketState": "CLOSED",
      "savedAt": 1779887584275
    },
    "LETRA": {
      "price": 164.44,
      "prevClose": 170.0,
      "exchange": "NSE",
      "lastTradeTime": 1779887584,
      "marketState": "CLOSED",
      "savedAt": 1779887584451
    },
    "LKPSEC": {
      "price": 18.48,
      "prevClose": 18.04,
      "exchange": "BSE",
      "lastTradeTime": 1779887586,
      "marketState": "CLOSED",
      "savedAt": 1779887586313
    },
    "MANGLO": {
      "price": 14.07,
      "prevClose": 13.6,
      "exchange": "NSE",
      "lastTradeTime": 1779887586,
      "marketState": "CLOSED",
      "savedAt": 1779887586485
    },
    "MAYUNI": {
      "price": 777.9,
      "prevClose": 744.8,
      "exchange": "NSE",
      "lastTradeTime": 1779887586,
      "marketState": "CLOSED",
      "savedAt": 1779887586688
    },
    "MININD": {
      "price": 1130.8,
      "prevClose": 1114.9,
      "exchange": "NSE",
      "lastTradeTime": 1779887586,
      "marketState": "CLOSED",
      "savedAt": 1779887586909
    },
    "MOOCAP": {
      "price": 16.0,
      "prevClose": 16.42,
      "exchange": "BSE",
      "lastTradeTime": 1779887587,
      "marketState": "CLOSED",
      "savedAt": 1779887587865
    },
    "NETW18": {
      "price": 31.27,
      "prevClose": 31.46,
      "exchange": "NSE",
      "lastTradeTime": 1779887588,
      "marketState": "CLOSED",
      "savedAt": 1779887588021
    },
    "NHPC": {
      "price": 80.68,
      "prevClose": 78.4,
      "exchange": "NSE",
      "lastTradeTime": 1779887589,
      "marketState": "CLOSED",
      "savedAt": 1779887589238
    },
    "NICEME": {
      "price": 28.69,
      "prevClose": 28.88,
      "exchange": "NSE",
      "lastTradeTime": 1779887589,
      "marketState": "CLOSED",
      "savedAt": 1779887589446
    },
    "ODYTEC": {
      "price": 38.97,
      "prevClose": 39.65,
      "exchange": "BSE",
      "lastTradeTime": 1779887590,
      "marketState": "CLOSED",
      "savedAt": 1779887590112
    },
    "OLAELE": {
      "price": 39.24,
      "prevClose": 37.52,
      "exchange": "NSE",
      "lastTradeTime": 1779887590,
      "marketState": "CLOSED",
      "savedAt": 1779887590271
    },
    "ONE97": {
      "price": 1128.2,
      "prevClose": 1133.4,
      "exchange": "NSE",
      "lastTradeTime": 1779887590,
      "marketState": "CLOSED",
      "savedAt": 1779887590443
    },
    "ORIHOT": {
      "price": 97.55,
      "prevClose": 99.0,
      "exchange": "NSE",
      "lastTradeTime": 1779887590,
      "marketState": "CLOSED",
      "savedAt": 1779887590664
    },
    "PANBIO": {
      "price": 413.15,
      "prevClose": 424.05,
      "exchange": "NSE",
      "lastTradeTime": 1779887590,
      "marketState": "CLOSED",
      "savedAt": 1779887590850
    },
    "PETLNG": {
      "price": 278.8,
      "prevClose": 280.45,
      "exchange": "NSE",
      "lastTradeTime": 1779887591,
      "marketState": "CLOSED",
      "savedAt": 1779887591061
    },
    "PHAOFF": {
      "price": 3.2,
      "prevClose": 3.12,
      "exchange": "BSE",
      "lastTradeTime": 1779887591,
      "marketState": "CLOSED",
      "savedAt": 1779887591775
    },
    "PHICAR": {
      "price": 287.5,
      "prevClose": 290.4,
      "exchange": "NSE",
      "lastTradeTime": 1779887592,
      "marketState": "CLOSED",
      "savedAt": 1779887592051
    },
    "POWTRA": {
      "price": 189.69,
      "prevClose": 191.58,
      "exchange": "NSE",
      "lastTradeTime": 1779887593,
      "marketState": "CLOSED",
      "savedAt": 1779887593282
    },
    "PRILI": {
      "price": 558.25,
      "prevClose": 563.0,
      "exchange": "NSE",
      "lastTradeTime": 1779887593,
      "marketState": "CLOSED",
      "savedAt": 1779887593544
    },
    "PTCIND": {
      "price": 30.7,
      "prevClose": 30.66,
      "exchange": "NSE",
      "lastTradeTime": 1779887593,
      "marketState": "CLOSED",
      "savedAt": 1779887593736
    },
    "RAMFOR": {
      "price": 566.1,
      "prevClose": 569.35,
      "exchange": "NSE",
      "lastTradeTime": 1779887593,
      "marketState": "CLOSED",
      "savedAt": 1779887593961
    },
    "RATINF": {
      "price": 35.38,
      "prevClose": 34.95,
      "exchange": "NSE",
      "lastTradeTime": 1779887594,
      "marketState": "CLOSED",
      "savedAt": 1779887594129
    },
    "RAVHEI": {
      "price": 39.14,
      "prevClose": 37.0,
      "exchange": "NSE",
      "lastTradeTime": 1779887594,
      "marketState": "CLOSED",
      "savedAt": 1779887594298
    },
    "RELIND": {
      "price": 1350.5,
      "prevClose": 1357.0,
      "exchange": "NSE",
      "lastTradeTime": 1779887594,
      "marketState": "CLOSED",
      "savedAt": 1779887594540
    },
    "SARFOO": {
      "price": 3.8,
      "prevClose": 3.72,
      "exchange": "NSE",
      "lastTradeTime": 1779887594,
      "marketState": "CLOSED",
      "savedAt": 1779887594702
    },
    "SBICAR": {
      "price": 625.25,
      "prevClose": 628.7,
      "exchange": "NSE",
      "lastTradeTime": 1779887594,
      "marketState": "CLOSED",
      "savedAt": 1779887594883
    },
    "SHAAGR": {
      "price": 0.49,
      "prevClose": 0.49,
      "exchange": "BSE",
      "lastTradeTime": 1779887595,
      "marketState": "CLOSED",
      "savedAt": 1779887595613
    },
    "SHICEM": {
      "price": 17.33,
      "prevClose": 17.07,
      "exchange": "BSE",
      "lastTradeTime": 1779887597,
      "marketState": "CLOSED",
      "savedAt": 1779887597361
    },
    "SINHOT": {
      "price": 74.08,
      "prevClose": 74.94,
      "exchange": "NSE",
      "lastTradeTime": 1779887597,
      "marketState": "CLOSED",
      "savedAt": 1779887597525
    },
    "SPESEM": {
      "price": 152.7,
      "prevClose": 152.9,
      "exchange": "BSE",
      "lastTradeTime": 1779887598,
      "marketState": "CLOSED",
      "savedAt": 1779887598196
    },
    "STABAN": {
      "price": 967.8,
      "prevClose": 969.8,
      "exchange": "NSE",
      "lastTradeTime": 1779887598,
      "marketState": "CLOSED",
      "savedAt": 1779887598443
    },
    "TANAER": {
      "price": 309.3,
      "prevClose": 304.5,
      "exchange": "BSE",
      "lastTradeTime": 1779887599,
      "marketState": "CLOSED",
      "savedAt": 1779887599172
    },
    "TATPOW": {
      "price": 425.8,
      "prevClose": 421.0,
      "exchange": "NSE",
      "lastTradeTime": 1779887599,
      "marketState": "CLOSED",
      "savedAt": 1779887599404
    },
    "TATSTE": {
      "price": 214.7,
      "prevClose": 210.25,
      "exchange": "NSE",
      "lastTradeTime": 1779887599,
      "marketState": "CLOSED",
      "savedAt": 1779887599614
    },
    "TCS": {
      "price": 2284.2,
      "prevClose": 2281.4,
      "exchange": "NSE",
      "lastTradeTime": 1779887599,
      "marketState": "CLOSED",
      "savedAt": 1779887599837
    },
    "TEXRAI": {
      "price": 108.93,
      "prevClose": 108.92,
      "exchange": "NSE",
      "lastTradeTime": 1779887600,
      "marketState": "CLOSED",
      "savedAt": 1779887600085
    },
    "TRIGLA": {
      "price": 6.6,
      "prevClose": 6.3,
      "exchange": "BSE",
      "lastTradeTime": 1779887601,
      "marketState": "CLOSED",
      "savedAt": 1779887601000
    },
    "TRILTD": {
      "price": 24.67,
      "prevClose": 24.46,
      "exchange": "NSE",
      "lastTradeTime": 1779887602,
      "marketState": "CLOSED",
      "savedAt": 1779887602288
    },
    "UNIBAN": {
      "price": 168.72,
      "prevClose": 167.95,
      "exchange": "NSE",
      "lastTradeTime": 1779887604,
      "marketState": "CLOSED",
      "savedAt": 1779887604224
    },
    "UNISPI": {
      "price": 1302.5,
      "prevClose": 1295.0,
      "exchange": "NSE",
      "lastTradeTime": 1779887604,
      "marketState": "CLOSED",
      "savedAt": 1779887604402
    },
    "VATWAB": {
      "price": 1547.0,
      "prevClose": 1502.0,
      "exchange": "NSE",
      "lastTradeTime": 1779887604,
      "marketState": "CLOSED",
      "savedAt": 1779887604614
    },
    "VIKMUL": {
      "price": 1.51,
      "prevClose": 1.45,
      "exchange": "NSE",
      "lastTradeTime": 1779887604,
      "marketState": "CLOSED",
      "savedAt": 1779887604791
    },
    "WEBENE": {
      "price": 112.47,
      "prevClose": 113.71,
      "exchange": "NSE",
      "lastTradeTime": 1779887604,
      "marketState": "CLOSED",
      "savedAt": 1779887604971
    },
    "WELIND": {
      "price": 139.45,
      "prevClose": 138.99,
      "exchange": "NSE",
      "lastTradeTime": 1779887605,
      "marketState": "CLOSED",
      "savedAt": 1779887605244
    },
    "YESBAN": {
      "price": 22.76,
      "prevClose": 22.8,
      "exchange": "NSE",
      "lastTradeTime": 1779887605,
      "marketState": "CLOSED",
      "savedAt": 1779887605425
    },
    "ZEEENT": {
      "price": 91.46,
      "prevClose": 82.78,
      "exchange": "NSE",
      "lastTradeTime": 1779887605,
      "marketState": "CLOSED",
      "savedAt": 1779887605648
    },
    "ZEEMED": {
      "price": 8.4,
      "prevClose": 8.01,
      "exchange": "NSE",
      "lastTradeTime": 1779887606,
      "marketState": "CLOSED",
      "savedAt": 1779887606888
    },
    "ZOMLIM": {
      "price": 256.51,
      "prevClose": 250.91,
      "exchange": "NSE",
      "lastTradeTime": 1779887607,
      "marketState": "CLOSED",
      "savedAt": 1779887607046
    },
    "ZUAAGR": {
      "price": 224.41,
      "prevClose": 225.49,
      "exchange": "NSE",
      "lastTradeTime": 1779887607,
      "marketState": "CLOSED",
      "savedAt": 1779887607221
    }
  },
  "savedAt": "2026-05-27T13:13:27.221641+00:00",
  "source": "github-actions"
}